shellen/__init__.py
shellen/archsconf.py
shellen/base.py
shellen/cli.py
shellen/fetcher.py
shellen/main.py
shellen/shell.py
shellen/asms/__init__.py
shellen/asms/asm.py
shellen/asms/baseexc.py
shellen/asms/disasm.py
shellen/opt/__init__.py
shellen/opt/appearance.py
shellen/opt/completer.py
shellen/syscalls/__init__.py
shellen/syscalls/base_handler.py
shellen/syscalls/linux_handler.py
shellen/syscalls/__pycache__/__init__.cpython-36.pyc
shellen/syscalls/__pycache__/base_handler.cpython-36.pyc
shellen/syscalls/__pycache__/linux_handler.cpython-36.pyc
shellen/syscalls/linux_tables/arm32.json
shellen/syscalls/linux_tables/arm_tb.json
shellen/syscalls/linux_tables/mips32.json
shellen/syscalls/linux_tables/mips32_o.json
shellen/syscalls/linux_tables/mips64.json
shellen/syscalls/linux_tables/ppc32.json
shellen/syscalls/linux_tables/ppc64.json
shellen/syscalls/linux_tables/sparc32.json
shellen/syscalls/linux_tables/sparc64.json
shellen/syscalls/linux_tables/x86_32.json
shellen/syscalls/linux_tables/x86_64.json
shellen-0.1.10.dist-info/DESCRIPTION.rst
shellen-0.1.10.dist-info/METADATA
shellen-0.1.10.dist-info/RECORD
shellen-0.1.10.dist-info/WHEEL
shellen-0.1.10.dist-info/entry_points.txt
shellen-0.1.10.dist-info/metadata.json
shellen-0.1.10.dist-info/top_level.txt
