Metadata-Version: 2.0
Name: shellen
Version: 0.1.10
Summary: Interactive environment for crafting shellcodes. Also, it just can be used as a simple assembler/disassembler
Home-page: https://github.com/merrychap/shellen
Author: Mike Evdokimov
Author-email: merrychap.c@gmail.com
License: MIT
Keywords: shellcode,pwn,assembler,disassembler,syscalls
Platform: UNKNOWN
Classifier: Environment :: Console
Classifier: Programming Language :: Python :: 3
Classifier: Programming Language :: Python :: 3.4
Classifier: Programming Language :: Python :: 3.5
Classifier: Programming Language :: Python :: 3.6
Classifier: Topic :: Security
Classifier: Topic :: Software Development :: Disassemblers
Classifier: Topic :: Software Development :: Assemblers
Classifier: Topic :: System :: Shells
Classifier: Topic :: Utilities
Classifier: Natural Language :: English
Classifier: License :: OSI Approved :: MIT License
Classifier: Intended Audience :: Information Technology
Requires-Python: >=3
Requires-Dist: capstone
Requires-Dist: colorama
Requires-Dist: keystone-engine
Requires-Dist: prompt-toolkit
Requires-Dist: pygments
Requires-Dist: requests
Requires-Dist: termcolor
Requires-Dist: terminaltables
